rss_feed_gen-1.3.1.dist-info/licenses/LICENSE
rssfeedgen/__init__.py
rssfeedgen/main.py
rss_feed_gen-1.3.1.dist-info/METADATA
rss_feed_gen-1.3.1.dist-info/WHEEL
rss_feed_gen-1.3.1.dist-info/entry_points.txt
rss_feed_gen-1.3.1.dist-info/top_level.txt
rss_feed_gen-1.3.1.dist-info/RECORD
